flexdict/__init__.py
flexdict-0.0.1a1.dist-info/LICENSE.txt
flexdict-0.0.1a1.dist-info/METADATA
flexdict-0.0.1a1.dist-info/WHEEL
flexdict-0.0.1a1.dist-info/top_level.txt
flexdict-0.0.1a1.dist-info/RECORD
