Metadata-Version: 2.1
Name: flexdict
Version: 0.0.1a1
Summary: Python dict with automatic and arbitrary levels of nesting along with additional utility methods.
Home-page: https://github.com/ozturkberkay/flexdict
Author: Berkay Öztürk
Author-email: info@berkayozturk.net
License: UNKNOWN
Project-URL: Bug Reports, https://github.com/ozturkberkay/FlexDict/issues
Project-URL: Source, https://github.com/ozturkberkay/FlexDict
Keywords: automatic arbitrary dict nesting
Platform: UNKNOWN
Classifier: Development Status :: 1 - Planning
Classifier: Intended Audience :: Developers
Classifier: Intended Audience :: Science/Research
Classifier: License :: OSI Approved :: MIT License
Classifier: Operating System :: OS Independent
Classifier: Programming Language :: Python :: 2.7
Classifier: Programming Language :: Python :: 3.3
Classifier: Programming Language :: Python :: 3.4
Classifier: Programming Language :: Python :: 3.5
Classifier: Programming Language :: Python :: 3.6
Classifier: Programming Language :: Python :: 3.7
Classifier: Programming Language :: Python :: 3.8
Classifier: Topic :: Software Development :: Libraries :: Python Modules
Classifier: Topic :: Utilities
Requires-Python: >=2.7
